EVBUS
