Metadata-Version: 1.1
Name: EVBUS
Version: 0.0.5
Summary: Estimate Variance Based on U-Statistics (EVBUS)
Home-page: https://github.com/liyao001/EVBUS
Author: Li Yao
Author-email: yaol17@mails.tsinghua.edu.cn
License: Apache 2.0
Platform: UNKNOWN
Classifier: Intended Audience :: Science/Research
Classifier: Operating System :: OS Independent
Classifier: Programming Language :: Python
Classifier: Topic :: Scientific/Engineering
